Metadata-Version: 2.1
Name: cloudtoken-plugin.centrify
Version: 0.1.764
Summary: Centrify plugin for Cloudtoken.
Home-page: https://bitbucket.org/atlassian/cloudtoken
Author: Atlassian Cloud Engineering
Author-email: cloud-team@atlassian.com
License: Apache
Platform: UNKNOWN
Requires-Python: >=3.5
Requires-Dist: cloudtoken (>=0.1.12)
Requires-Dist: pyquery (>=1.3.0)
Requires-Dist: requests (>=2.9.1)
Requires-Dist: lxml (>=4.2.1)
